MANIFEST.in
README.md
setup.cfg
setup.py
rocketmq/__init__.py
rocketmq/client.py
rocketmq/consts.py
rocketmq/exceptions.py
rocketmq/ffi.py
rocketmq/librocketmq.so
rocketmq_python_cvs.egg-info/PKG-INFO
rocketmq_python_cvs.egg-info/SOURCES.txt
rocketmq_python_cvs.egg-info/dependency_links.txt
rocketmq_python_cvs.egg-info/requires.txt
rocketmq_python_cvs.egg-info/top_level.txt
samples/__init__.py
samples/consumer.py
samples/producer.py