Metadata-Version: 2.1
Name: rocketmq-python-cvs
Version: 2.1.0.1
Summary: RocketMQ Python Client CVS
Author: karl zhou
Author-email: qipeng@conversant.com.sg
Keywords: rocketmq
Classifier: Operating System :: MacOS
Classifier: Operating System :: POSIX
Classifier: Operating System :: POSIX :: Linux
Classifier: Programming Language :: Python
Classifier: Programming Language :: Python :: 2.7
Classifier: Programming Language :: Python :: 3.5
Classifier: Programming Language :: Python :: 3.6
Classifier: Programming Language :: Python :: 3.7
Classifier: Programming Language :: Python :: Implementation :: CPython
